Metadata-Version: 1.0
Name: distributions-dirkkadijk
Version: 0.1
Summary: Gaussian distributions created by Dirk Kadijk
Home-page: UNKNOWN
Author: Dirk Kadijk
Author-email: dkadijk@me.com
License: UNKNOWN
Platform: UNKNOWN
